tac_test_package/AutoTAC.py
tac_test_package/TAC.py
tac_test_package/__init__.py
tac_test_package/models/AutoTAC.py
tac_test_package/models/TAC.py
tac_test_package/models/__init_.py
tac_test_package/models/__init__.py
tac_test_package/models/run/__init__.py
tac_test_package/models/run/multiple.py
tac_test_package/models/run/single.py
tac_test_package/models/utils/__init__.py
tac_test_package/models/utils/format_save.py
tac_test_package/models/utils/metrics.py
tac_test_package/models/utils/plots.py
tac_test_package/run/__init__.py
tac_test_package/run/multiple.py
tac_test_package/run/single.py
tac_test_package/utils/__init__.py
tac_test_package/utils/format_save.py
tac_test_package/utils/metrics.py
tac_test_package/utils/plots.py
Conect2pyPackage-0.0.1.dist-info/LICENSE
Conect2pyPackage-0.0.1.dist-info/METADATA
Conect2pyPackage-0.0.1.dist-info/WHEEL
Conect2pyPackage-0.0.1.dist-info/top_level.txt
Conect2pyPackage-0.0.1.dist-info/RECORD
